flacopyus/__init__.py
flacopyus/__main__.py
flacopyus/args.py
flacopyus/assets.py
flacopyus/cli.py
flacopyus/filesys.py
flacopyus/funs.py
flacopyus/main.py
flacopyus/opus.py
flacopyus/py.typed
flacopyus/spr.py
flacopyus/stdio.py
flacopyus/test.py
flacopyus/audio/drum-loop.flac
flacopyus/audio/system-shutdown.wav
flacopyus/bin/LICENSE
flacopyus/bin/opusenc.exe
flacopyus/pyinstaller/hook-flacopyus.py
flacopyus-0.3.5.dist-info/licenses/LICENSE
flacopyus-0.3.5.dist-info/licenses/flacopyus/bin/LICENSE
flacopyus-0.3.5.dist-info/METADATA
flacopyus-0.3.5.dist-info/WHEEL
flacopyus-0.3.5.dist-info/entry_points.txt
flacopyus-0.3.5.dist-info/top_level.txt
flacopyus-0.3.5.dist-info/RECORD
