Metadata-Version: 2.4
Name: flacopyus
Version: 0.3.5
Summary: CLI tool to mirror your FLAC audio library to a portable lossy Opus version
Maintainer-email: curegit <contact@curegit.jp>
License-Expression: GPL-3.0-or-later
Project-URL: homepage, https://github.com/curegit/flacopyus
Project-URL: repository, https://github.com/curegit/flacopyus.git
Keywords: FLAC,Opus,music library,file syncing,portable audio player
Classifier: Programming Language :: Python :: 3 :: Only
Classifier: Topic :: Multimedia :: Sound/Audio :: Conversion
Classifier: Typing :: Typed
Requires-Python: >=3.14
License-File: LICENSE
License-File: flacopyus/bin/LICENSE
Requires-Dist: rich>=14
Provides-Extra: dev
Requires-Dist: pip; extra == "dev"
Requires-Dist: build; extra == "dev"
Requires-Dist: twine; extra == "dev"
Requires-Dist: ruff; extra == "dev"
Requires-Dist: mypy; extra == "dev"
Dynamic: license-file
